llm_openai_images.py
llm_openai_images-0.3.1.dist-info/licenses/LICENSE
llm_openai_images-0.3.1.dist-info/METADATA
llm_openai_images-0.3.1.dist-info/WHEEL
llm_openai_images-0.3.1.dist-info/entry_points.txt
llm_openai_images-0.3.1.dist-info/top_level.txt
llm_openai_images-0.3.1.dist-info/RECORD
