Metadata-Version: 2.4
Name: llm-openai-images
Version: 0.3.1
Summary: LLM plugin for OpenAI and Google image generation and editing
Author: Graham Bing
License: Apache-2.0
Project-URL: Homepage, https://github.com/gdbing/llm-openai-images
Project-URL: Issues, https://github.com/gdbing/llm-openai-images/issues
Project-URL: Changelog, https://github.com/gdbing/llm-openai-images/releases
Requires-Python: >=3.9
License-File: LICENSE
Requires-Dist: llm>=0.23
Requires-Dist: httpx>=0.27.0
Requires-Dist: openai>=1.76.0
Dynamic: license-file
